info/gianlucacosta/eos/core/__init__.py
info/gianlucacosta/eos/core/db/__init__.py
info/gianlucacosta/eos/core/db/sqlite/__init__.py
info/gianlucacosta/eos/core/db/sqlite/serializer.py
info/gianlucacosta/eos/core/functional/__init__.py
info/gianlucacosta/eos/core/functional/callback.py
info/gianlucacosta/eos/core/functional/retries.py
info/gianlucacosta/eos/core/io/__init__.py
info/gianlucacosta/eos/core/io/files/__init__.py
info/gianlucacosta/eos/core/io/files/temporary.py
info/gianlucacosta/eos/core/io/serializing/__init__.py
info/gianlucacosta/eos/core/io/serializing/delayed.py
info/gianlucacosta/eos/core/logic/__init__.py
info/gianlucacosta/eos/core/logic/ranges.py
info/gianlucacosta/eos/core/multiprocessing/__init__.py
info/gianlucacosta/eos/core/multiprocessing/pool/__init__.py
info/gianlucacosta/eos/core/multiprocessing/pool/facade.py
info/gianlucacosta/eos/core/py.typed
info/gianlucacosta/eos/core/reflection/__init__.py
info/gianlucacosta/eos/core/strings.py
info/gianlucacosta/eos/core/threading/__init__.py
info/gianlucacosta/eos/core/threading/atomic.py
info/gianlucacosta/eos/core/threading/cancelable.py
info/gianlucacosta/eos/core/threading/queues/__init__.py
info/gianlucacosta/eos/core/threading/queues/adaptive.py
info/gianlucacosta/eos/core/threading/safe.py
info.gianlucacosta.eos.core-1.0.0.dist-info/LICENSE
info.gianlucacosta.eos.core-1.0.0.dist-info/WHEEL
info.gianlucacosta.eos.core-1.0.0.dist-info/METADATA
info.gianlucacosta.eos.core-1.0.0.dist-info/RECORD
