Metadata-Version: 2.1
Name: info.gianlucacosta.eos.core
Version: 1.0.0
Summary: Type-checked, dependency-free utility library for modern Python
Home-page: https://github.com/giancosta86/Eos-core
License: MIT
Keywords: library,type-checked,modern,utilities
Author: Gianluca Costa
Author-email: gianluca@gianlucacosta.info
Requires-Python: >=3.10,<4.0
Classifier: Development Status :: 5 - Production/Stable
Classifier: Environment :: Console
Classifier: Intended Audience :: Developers
Classifier: License :: OSI Approved :: MIT License
Classifier: Operating System :: OS Independent
Classifier: Programming Language :: Python
Classifier: Programming Language :: Python :: 3
Classifier: Programming Language :: Python :: 3.10
Classifier: Topic :: Utilities
Project-URL: Documentation, https://github.com/giancosta86/Eos-core
Project-URL: Repository, https://github.com/giancosta86/Eos-core
